{"cameraMode":{"drawMode":0,"name":"Shaded","section":"Shading Mode"},"sceneLighting":false,"audioPlay":false,"sceneViewState":{"showFog":true,"showMaterialUpdate":false,"showSkybox":false,"showFlares":true,"showImageEffects":true,"showParticleSystems":true},"in2DMode":false,"pivot":{"x":1.7881393432617188e-7,"y":1.2173446416854859,"z":-0.0738823413848877},"rotation":{"x":0.08388479799032211,"y":0.6270377039909363,"z":-0.06818104535341263,"w":0.771456241607666},"size":1.9156255722045899,"orthographic":false}