{"cameraMode":{"drawMode":0,"name":"Shaded","section":"Shading Mode"},"sceneLighting":false,"audioPlay":false,"sceneViewState":{"showFog":true,"showMaterialUpdate":false,"showSkybox":false,"showFlares":true,"showImageEffects":true,"showParticleSystems":true},"in2DMode":false,"pivot":{"x":0.22631792724132539,"y":0.5808468461036682,"z":1.7086832523345948},"rotation":{"x":0.12091322243213654,"y":0.752570390701294,"z":-0.14419592916965486,"w":0.6310569047927856},"size":0.9370285868644714,"orthographic":false}